ai_git_assistant/__init__.py
ai_git_assistant/__main__.py
ai_git_assistant-1.0.5.dist-info/licenses/LICENSE
tests/__init__.py
tests/test_git_detection.py
tests/tests_cli.py
tests/tests_git_utils.py
ai_git_assistant-1.0.5.dist-info/METADATA
ai_git_assistant-1.0.5.dist-info/WHEEL
ai_git_assistant-1.0.5.dist-info/entry_points.txt
ai_git_assistant-1.0.5.dist-info/top_level.txt
ai_git_assistant-1.0.5.dist-info/RECORD
