Metadata-Version: 2.4
Name: ai-git-assistant
Version: 1.0.5
Summary: Asistente inteligente para atuomatizar tareas de Git y GitHub
Home-page: https://github.com/LuisGH28/git_assistant
Author: Luis Gonzalez
Author-email: Luis Gonzalez <luisgnzhdz@gmail.com>
License-Expression: MIT
Project-URL: Homepage, https://github.com/LuisGH28/git_assitant
Classifier: Programming Language :: Python :: 3
Classifier: Operating System :: OS Independent
Requires-Python: >=3.6
License-File: LICENSE
Requires-Dist: scikit-learn
Requires-Dist: numpy
Requires-Dist: joblib
Dynamic: author
Dynamic: home-page
Dynamic: license-file
Dynamic: requires-python
